libcachesim-0.3.3.post3.dist-info/RECORD
libcachesim-0.3.3.post3.dist-info/WHEEL
libcachesim-0.3.3.post3.dist-info/METADATA
libcachesim-0.3.3.post3.dist-info/licenses/LICENSE
libcachesim/__init__.pyi
libcachesim/protocols.py
libcachesim/util.py
libcachesim/_s3_cache.py
libcachesim/libcachesim_python.cpython-310-darwin.so
libcachesim/trace_analyzer.py
libcachesim/cache.py
libcachesim/__init__.py
libcachesim/trace_reader.py
libcachesim/synthetic_reader.py
libcachesim/.dylibs/libpcre2-8.0.dylib
libcachesim/.dylibs/libglib-2.0.0.dylib
libcachesim/.dylibs/libomp.dylib
libcachesim/.dylibs/libxgboost.dylib
libcachesim/.dylibs/libintl.8.dylib
libcachesim/.dylibs/lib_lightgbm.dylib
libcachesim/.dylibs/libzstd.1.5.7.dylib
