Metadata-Version: 2.2
Name: libcachesim
Version: 0.3.3.post3
Summary: Python bindings for libCacheSim
Keywords: performance,cache,simulator
Classifier: Intended Audience :: Developers
Classifier: License :: OSI Approved :: GNU General Public License v3 or later (GPLv3+)
Classifier: Programming Language :: Python :: 3.9
Classifier: Programming Language :: Python :: 3.10
Classifier: Programming Language :: Python :: 3.11
Classifier: Programming Language :: Python :: 3.12
Classifier: Programming Language :: Python :: 3.13
Requires-Python: >=3.9
Requires-Dist: numpy>=1.20.0
Requires-Dist: boto3
Requires-Dist: pybind11>=2.10.0
Requires-Dist: pytest>=8.4.1
Provides-Extra: test
Requires-Dist: pytest; extra == "test"
Provides-Extra: dev
Requires-Dist: pytest; extra == "dev"
Requires-Dist: pre-commit; extra == "dev"
Requires-Dist: ruff>=0.7.0; extra == "dev"
Requires-Dist: mypy>=1.0.0; extra == "dev"
